Metadata-Version: 2.1
Name: tkitJson
Version: 0.0.0.3
Summary: Terry toolkit
Home-page: http://www.terrychan.org/tkitJson
Author: Terry Chan
Author-email: napoler2008@gmail.com
License: UNKNOWN
Platform: UNKNOWN
